gully.py
gully-0.3.1.dist-info/LICENSE
gully-0.3.1.dist-info/WHEEL
gully-0.3.1.dist-info/METADATA
gully-0.3.1.dist-info/RECORD
