Metadata-Version: 2.1
Name: gully
Version: 0.3.1
Summary: Simple real time data stream manipulation.
Home-page: https://github.com/ZechCodes/gully
License: MIT
Keywords: data,stream,realtime,framework,events
Author: Zech Zimmerman
Author-email: hi@zech.codes
Requires-Python: >=3.7,<4.0
Classifier: Development Status :: 5 - Production/Stable
Classifier: Intended Audience :: Developers
Classifier: License :: OSI Approved :: MIT License
Classifier: Programming Language :: Python :: 3
Classifier: Programming Language :: Python :: 3.7
Classifier: Programming Language :: Python :: 3.8
Classifier: Programming Language :: Python :: 3.9
Classifier: Topic :: Software Development :: Libraries :: Application Frameworks
Project-URL: Documentation, https://github.com/ZechCodes/gully/blob/main/readme.md
Project-URL: Repository, https://github.com/ZechCodes/gully
